object_detection_ctg/__init__.py
object_detection_ctg/eval_util.py
object_detection_ctg/eval_util_test.py
object_detection_ctg/export_inference_graph.py
object_detection_ctg/export_tflite_graph_lib_tf2.py
object_detection_ctg/export_tflite_graph_lib_tf2_test.py
object_detection_ctg/export_tflite_graph_tf2.py
object_detection_ctg/export_tflite_ssd_graph.py
object_detection_ctg/export_tflite_ssd_graph_lib.py
object_detection_ctg/export_tflite_ssd_graph_lib_tf1_test.py
object_detection_ctg/exporter.py
object_detection_ctg/exporter_lib_tf2_test.py
object_detection_ctg/exporter_lib_v2.py
object_detection_ctg/exporter_main_v2.py
object_detection_ctg/exporter_tf1_test.py
object_detection_ctg/inputs.py
object_detection_ctg/inputs_test.py
object_detection_ctg/model_hparams.py
object_detection_ctg/model_lib.py
object_detection_ctg/model_lib_tf1_test.py
object_detection_ctg/model_lib_tf2_test.py
object_detection_ctg/model_lib_v2.py
object_detection_ctg/model_main.py
object_detection_ctg/model_main_tf2.py
object_detection_ctg/model_tpu_main.py
object_detection_ctg/setup.py
object_detection_ctg.egg-info/PKG-INFO
object_detection_ctg.egg-info/SOURCES.txt
object_detection_ctg.egg-info/dependency_links.txt
object_detection_ctg.egg-info/requires.txt
object_detection_ctg.egg-info/top_level.txt
object_detection_ctg/anchor_generators/__init__.py
object_detection_ctg/anchor_generators/flexible_grid_anchor_generator.py
object_detection_ctg/anchor_generators/flexible_grid_anchor_generator_test.py
object_detection_ctg/anchor_generators/grid_anchor_generator.py
object_detection_ctg/anchor_generators/grid_anchor_generator_test.py
object_detection_ctg/anchor_generators/multiple_grid_anchor_generator.py
object_detection_ctg/anchor_generators/multiple_grid_anchor_generator_test.py
object_detection_ctg/anchor_generators/multiscale_grid_anchor_generator.py
object_detection_ctg/anchor_generators/multiscale_grid_anchor_generator_test.py
object_detection_ctg/box_coders/__init__.py
object_detection_ctg/box_coders/faster_rcnn_box_coder.py
object_detection_ctg/box_coders/faster_rcnn_box_coder_test.py
object_detection_ctg/box_coders/keypoint_box_coder.py
object_detection_ctg/box_coders/keypoint_box_coder_test.py
