Metadata-Version: 1.2
Name: object-detection-ctg
Version: 0.1
Summary: Tensorflow CTG Object Detection Library
Home-page: UNKNOWN
License: UNKNOWN
Platform: UNKNOWN
Requires-Python: >3.6
